rsbac_tools-0.3.3.31.data/scripts/rsbac-backup
rsbac_tools-0.3.3.31.data/scripts/rsbac-ff-shields
rsbac_tools-0.3.3.31.data/scripts/rsbac-ps-jail
rsbac_tools-0.3.3.31.data/scripts/rsbac-run-jail
rsbac_tools-0.3.3.31.data/scripts/rsbac-symlink-redirect
rsbactools/__about__.py
rsbactools/__init__.py
rsbactools/__version__.py
rsbactools/backup.py
rsbactools/backup_ng.py
rsbactools/config.py
rsbactools/converter.py
rsbactools/ff.py
rsbactools/jail.py
rsbactools/rsbac.py
rsbac_tools-0.3.3.31.dist-info/AUTHORS.txt
rsbac_tools-0.3.3.31.dist-info/LICENSE.txt
rsbac_tools-0.3.3.31.dist-info/METADATA
rsbac_tools-0.3.3.31.dist-info/WHEEL
rsbac_tools-0.3.3.31.dist-info/top_level.txt
rsbac_tools-0.3.3.31.dist-info/RECORD
