Metadata-Version: 2.1
Name: rsbac-tools
Version: 0.3.3.31
Summary: Command-line tools for daily tasks on a RSBAC system.
Home-page: https://bitbucket.org/igraltist/rsbac-tools
Author: Jens Kasten
Author-email: jens@kasten-edv.de
License: GNU GPLv3
Keywords: security,rsbac
Platform: UNKNOWN
Classifier: Intended Audience :: System Administrators
Classifier: License :: OSI Approved :: GNU General Public License v3 (GPLv3)
Classifier: Operating System :: POSIX :: Linux
Classifier: Topic :: System :: Systems Administration
